{
  "user_id": 756603394,
  "query": "рубашка",
  "timestamp": "2025-05-28T16:54:47.275281",
  "lime_urls": [],
  "lichi_urls": [
    "https://lichi.com/ru/ru/product/49428",
    "https://lichi.com/ru/ru/product/49427",
    "https://lichi.com/ru/ru/product/47210",
    "https://lichi.com/ru/ru/product/48091",
    "https://lichi.com/ru/ru/product/48092",
    "https://lichi.com/ru/ru/product/48093",
    "https://lichi.com/ru/ru/product/47281",
    "https://lichi.com/ru/ru/product/47528"
  ],
  "loverepublic_urls": [],
  "befree_urls": []
}